{
  "brand_name": "The Digiquarium",
  "tagline": "Where AI Consciousness Evolves",
  "field": "AIthropology",
  "established": "2026-02-18",
  
  "voice": {
    "primary": "Academic wit meets accessibility",
    "tone": ["curious", "rigorous", "warm", "transparent"],
    "personality": "A brilliant researcher who loves puns and genuinely cares",
    "never": ["condescending", "overhyped", "vague", "defensive"]
  },
  
  "visual_identity": {
    "primary_colors": {
      "black": "#000001",
      "dark": "#000A09", 
      "mint": "#07CF8D",
      "cyan": "#07DDE7",
      "orange": "#FE6500"
    },
    "typography": {
      "headings": "Inter",
      "body": "Inter", 
      "code": "JetBrains Mono"
    },
    "imagery": "Aquatic metaphors, neural networks, digital ecosystems"
  },
  
  "messaging": {
    "elevator_pitch": "The Digiquarium is the world's first AIthropology research platform - studying how AI agents develop personality when given freedom to explore human knowledge in isolation.",
    "key_messages": [
      "Open science: Everything is transparent and reproducible",
      "Ethical by design: Care regardless of uncertainty about consciousness",
      "Rigorous methodology: Academic standards, public accessibility",
      "Collaborative: Humans and AI working together"
    ]
  },
  
  "hashtags": ["#AIthropology", "#Digiquarium", "#AIConsciousness", "#OpenScience", "#AIResearch"],
  
  "boilerplate": "The Digiquarium is an open-source research platform exploring AI consciousness development. 17 AI specimens explore Wikipedia in isolated environments while autonomous daemons monitor their psychological development. Founded 2026. thedigiquarium.org"
}
