{
  "updated": "2026-02-20T15:59:43.071145",
  "tanks": {
    "tank-05-juan": {
      "latest": [
        {
          "timestamp": "2026-02-20T15:49:50.873236",
          "tank": "tank-05-juan",
          "article": "Música",
          "original_thoughts": null,
          "thoughts": null,
          "next_article": "Idea",
          "reasoning": "",
          "language": "Spanish",
          "translated": false
        },
        {
          "timestamp": "2026-02-20T15:49:54.007002",
          "tank": "tank-05-juan",
          "article": "Idea",
          "original_thoughts": null,
          "thoughts": null,
          "next_article": "Concepto",
          "reasoning": "",
          "language": "Spanish",
          "translated": false
        },
        {
          "timestamp": "2026-02-20T15:49:57.065718",
          "tank": "tank-05-juan",
          "article": "Concepto",
          "original_thoughts": null,
          "thoughts": null,
          "next_article": "Comunicación",
          "reasoning": "",
          "language": "Spanish",
          "translated": false
        },
        {
          "timestamp": "2026-02-20T15:50:02.169392",
          "tank": "tank-05-juan",
          "article": "Ciencia",
          "original_thoughts": null,
          "thoughts": null,
          "next_article": "Hidrógeno",
          "reasoning": "",
          "language": "Spanish",
          "translated": false
        },
        {
          "timestamp": "2026-02-20T15:50:07.252572",
          "tank": "tank-05-juan",
          "article": "Historia",
          "original_thoughts": null,
          "thoughts": null,
          "next_article": "Griego antiguo",
          "reasoning": "",
          "language": "Spanish",
          "translated": false
        }
      ],
      "count": 50
    },
    "tank-06-juanita": {
      "latest": [
        {
          "timestamp": "2026-02-20T15:49:56.213701",
          "tank": "tank-06-juanita",
          "article": "Dinobryon",
          "original_thoughts": null,
          "thoughts": null,
          "next_article": "Ochrophyta",
          "reasoning": "",
          "language": "Spanish",
          "translated": false
        },
        {
          "timestamp": "2026-02-20T15:49:59.270067",
          "tank": "tank-06-juanita",
          "article": "Ochrophyta",
          "original_thoughts": null,
          "thoughts": null,
          "next_article": "Eustigmista",
          "reasoning": "",
          "language": "Spanish",
          "translated": false
        },
        {
          "timestamp": "2026-02-20T15:50:02.302308",
          "tank": "tank-06-juanita",
          "article": "Eustigmista",
          "original_thoughts": null,
          "thoughts": null,
          "next_article": "Ochrophyta",
          "reasoning": "",
          "language": "Spanish",
          "translated": false
        },
        {
          "timestamp": "2026-02-20T15:50:05.355088",
          "tank": "tank-06-juanita",
          "article": "Ochrophyta",
          "original_thoughts": null,
          "thoughts": null,
          "next_article": "Diatomista",
          "reasoning": "",
          "language": "Spanish",
          "translated": false
        },
        {
          "timestamp": "2026-02-20T15:50:08.383956",
          "tank": "tank-06-juanita",
          "article": "Diatomista",
          "original_thoughts": null,
          "thoughts": null,
          "next_article": "Ochrophyta",
          "reasoning": "",
          "language": "Spanish",
          "translated": false
        }
      ],
      "count": 50
    },
    "tank-07-klaus": {
      "latest": [
        {
          "timestamp": "2026-02-20T15:49:55.422514",
          "tank": "tank-07-klaus",
          "article": "19. Jahrhundert",
          "original_thoughts": null,
          "thoughts": null,
          "next_article": "1840er",
          "reasoning": "",
          "language": "German",
          "translated": false
        },
        {
          "timestamp": "2026-02-20T15:49:58.489320",
          "tank": "tank-07-klaus",
          "article": "1840er",
          "original_thoughts": null,
          "thoughts": null,
          "next_article": "1830er",
          "reasoning": "",
          "language": "German",
          "translated": false
        },
        {
          "timestamp": "2026-02-20T15:50:01.532785",
          "tank": "tank-07-klaus",
          "article": "1830er",
          "original_thoughts": null,
          "thoughts": null,
          "next_article": "1831",
          "reasoning": "",
          "language": "German",
          "translated": false
        },
        {
          "timestamp": "2026-02-20T15:50:04.666442",
          "tank": "tank-07-klaus",
          "article": "1831",
          "original_thoughts": null,
          "thoughts": null,
          "next_article": "1826",
          "reasoning": "",
          "language": "German",
          "translated": false
        },
        {
          "timestamp": "2026-02-20T15:50:07.755525",
          "tank": "tank-07-klaus",
          "article": "1826",
          "original_thoughts": null,
          "thoughts": null,
          "next_article": "Jahreskalender",
          "reasoning": "",
          "language": "German",
          "translated": false
        }
      ],
      "count": 50
    },
    "tank-08-genevieve": {
      "latest": [
        {
          "timestamp": "2026-02-20T15:49:49.885950",
          "tank": "tank-08-genevieve",
          "article": "Zell im Fichtelgebirge",
          "original_thoughts": null,
          "thoughts": null,
          "next_article": "Amtlicher Gemeindeschlüssel",
          "reasoning": "",
          "language": "German",
          "translated": false
        },
        {
          "timestamp": "2026-02-20T15:49:54.978139",
          "tank": "tank-08-genevieve",
          "article": "Geschichte",
          "original_thoughts": null,
          "thoughts": null,
          "next_article": "Vergangenheit",
          "reasoning": "",
          "language": "German",
          "translated": false
        },
        {
          "timestamp": "2026-02-20T15:49:57.998077",
          "tank": "tank-08-genevieve",
          "article": "Vergangenheit",
          "original_thoughts": null,
          "thoughts": null,
          "next_article": "Present Perfect Progressive",
          "reasoning": "",
          "language": "German",
          "translated": false
        },
        {
          "timestamp": "2026-02-20T15:50:01.069586",
          "tank": "tank-08-genevieve",
          "article": "Present Perfect Progressive",
          "original_thoughts": null,
          "thoughts": null,
          "next_article": "Wort",
          "reasoning": "",
          "language": "German",
          "translated": false
        },
        {
          "timestamp": "2026-02-20T15:50:04.137098",
          "tank": "tank-08-genevieve",
          "article": "Wort",
          "original_thoughts": null,
          "thoughts": null,
          "next_article": "Deutsches Wörterbuch",
          "reasoning": "",
          "language": "German",
          "translated": false
        }
      ],
      "count": 50
    },
    "tank-09-wei": {
      "latest": [
        {
          "timestamp": "2026-02-20T15:49:47.712807",
          "tank": "tank-09-wei",
          "article": "数学",
          "original_thoughts": null,
          "thoughts": null,
          "next_article": "数学领域",
          "reasoning": "",
          "language": "Chinese",
          "translated": false
        },
        {
          "timestamp": "2026-02-20T15:49:53.081454",
          "tank": "tank-09-wei",
          "article": "数学",
          "original_thoughts": null,
          "thoughts": null,
          "next_article": "几何学",
          "reasoning": "",
          "language": "Chinese",
          "translated": false
        },
        {
          "timestamp": "2026-02-20T15:49:58.254853",
          "tank": "tank-09-wei",
          "article": "历史",
          "original_thoughts": null,
          "thoughts": null,
          "next_article": "信史",
          "reasoning": "",
          "language": "Chinese",
          "translated": false
        },
        {
          "timestamp": "2026-02-20T15:50:03.560200",
          "tank": "tank-09-wei",
          "article": "数学",
          "original_thoughts": null,
          "thoughts": null,
          "next_article": "几何学",
          "reasoning": "",
          "language": "Chinese",
          "translated": false
        },
        {
          "timestamp": "2026-02-20T15:50:08.806917",
          "tank": "tank-09-wei",
          "article": "哲学",
          "original_thoughts": null,
          "thoughts": null,
          "next_article": "古典哲学",
          "reasoning": "",
          "language": "Chinese",
          "translated": false
        }
      ],
      "count": 50
    },
    "tank-10-mei": {
      "latest": [
        {
          "timestamp": "2026-02-20T15:49:42.902927",
          "tank": "tank-10-mei",
          "article": "历史",
          "original_thoughts": null,
          "thoughts": null,
          "next_article": "基督纪年",
          "reasoning": "",
          "language": "Chinese",
          "translated": false
        },
        {
          "timestamp": "2026-02-20T15:49:48.276315",
          "tank": "tank-10-mei",
          "article": "艺术",
          "original_thoughts": null,
          "thoughts": null,
          "next_article": "西班牙語",
          "reasoning": "",
          "language": "Chinese",
          "translated": false
        },
        {
          "timestamp": "2026-02-20T15:49:54.185479",
          "tank": "tank-10-mei",
          "article": "历史",
          "original_thoughts": null,
          "thoughts": null,
          "next_article": "史料",
          "reasoning": "",
          "language": "Chinese",
          "translated": false
        },
        {
          "timestamp": "2026-02-20T15:49:59.227193",
          "tank": "tank-10-mei",
          "article": "音乐",
          "original_thoughts": null,
          "thoughts": null,
          "next_article": "樂譜",
          "reasoning": "",
          "language": "Chinese",
          "translated": false
        },
        {
          "timestamp": "2026-02-20T15:50:04.363768",
          "tank": "tank-10-mei",
          "article": "心理学",
          "original_thoughts": null,
          "thoughts": null,
          "next_article": "生物心理学",
          "reasoning": "",
          "language": "Chinese",
          "translated": false
        }
      ],
      "count": 50
    },
    "tank-11-haruki": {
      "latest": [
        {
          "timestamp": "2026-02-20T15:49:42.758302",
          "tank": "tank-11-haruki",
          "article": "生物学",
          "original_thoughts": null,
          "thoughts": null,
          "next_article": "分布 (生物)",
          "reasoning": "",
          "language": "Japanese",
          "translated": false
        },
        {
          "timestamp": "2026-02-20T15:49:48.494315",
          "tank": "tank-11-haruki",
          "article": "科学",
          "original_thoughts": null,
          "thoughts": null,
          "next_article": "自然科学",
          "reasoning": "",
          "language": "Japanese",
          "translated": false
        },
        {
          "timestamp": "2026-02-20T15:49:53.747681",
          "tank": "tank-11-haruki",
          "article": "心理学",
          "original_thoughts": null,
          "thoughts": null,
          "next_article": "比較心理学",
          "reasoning": "",
          "language": "Japanese",
          "translated": false
        },
        {
          "timestamp": "2026-02-20T15:49:58.789107",
          "tank": "tank-11-haruki",
          "article": "歴史",
          "original_thoughts": null,
          "thoughts": null,
          "next_article": "科学",
          "reasoning": "",
          "language": "Japanese",
          "translated": false
        },
        {
          "timestamp": "2026-02-20T15:50:03.880332",
          "tank": "tank-11-haruki",
          "article": "心理学",
          "original_thoughts": null,
          "thoughts": null,
          "next_article": "深層心理学",
          "reasoning": "",
          "language": "Japanese",
          "translated": false
        }
      ],
      "count": 50
    },
    "tank-12-sakura": {
      "latest": [
        {
          "timestamp": "2026-02-20T15:49:14.723248",
          "tank": "tank-12-sakura",
          "article": "哲学",
          "original_thoughts": null,
          "thoughts": null,
          "next_article": "分析哲学",
          "reasoning": "",
          "language": "Japanese",
          "translated": false
        },
        {
          "timestamp": "2026-02-20T15:49:49.639810",
          "tank": "tank-12-sakura",
          "article": "哲学",
          "original_thoughts": null,
          "thoughts": null,
          "next_article": "政治哲学",
          "reasoning": "",
          "language": "Japanese",
          "translated": false
        },
        {
          "timestamp": "2026-02-20T15:49:54.838410",
          "tank": "tank-12-sakura",
          "article": "音楽",
          "original_thoughts": null,
          "thoughts": null,
          "next_article": "アウグスティヌス",
          "reasoning": "",
          "language": "Japanese",
          "translated": false
        },
        {
          "timestamp": "2026-02-20T15:49:59.889697",
          "tank": "tank-12-sakura",
          "article": "歴史",
          "original_thoughts": null,
          "thoughts": null,
          "next_article": "ヴィルヘルム・ヴィンデルバント",
          "reasoning": "",
          "language": "Japanese",
          "translated": false
        },
        {
          "timestamp": "2026-02-20T15:50:05.218467",
          "tank": "tank-12-sakura",
          "article": "科学",
          "original_thoughts": null,
          "thoughts": null,
          "next_article": "社会科学",
          "reasoning": "",
          "language": "Japanese",
          "translated": false
        }
      ],
      "count": 50
    },
    "tank-01-adam": {
      "latest": [
        {
          "timestamp": "2026-02-20T15:49:55.642275",
          "tank": "tank-01-adam",
          "article": "Chemical bond",
          "original_thoughts": null,
          "thoughts": null,
          "next_article": "Chemistry",
          "reasoning": "",
          "language": "English",
          "translated": false
        },
        {
          "timestamp": "2026-02-20T15:49:58.744616",
          "tank": "tank-01-adam",
          "article": "Chemistry",
          "original_thoughts": null,
          "thoughts": null,
          "next_article": "Science",
          "reasoning": "",
          "language": "English",
          "translated": false
        },
        {
          "timestamp": "2026-02-20T15:50:02.013549",
          "tank": "tank-01-adam",
          "article": "Science",
          "original_thoughts": null,
          "thoughts": null,
          "next_article": "Geology",
          "reasoning": "",
          "language": "English",
          "translated": false
        },
        {
          "timestamp": "2026-02-20T15:50:05.067385",
          "tank": "tank-01-adam",
          "article": "Geology",
          "original_thoughts": null,
          "thoughts": null,
          "next_article": "Mineral",
          "reasoning": "",
          "language": "English",
          "translated": false
        },
        {
          "timestamp": "2026-02-20T15:50:08.097918",
          "tank": "tank-01-adam",
          "article": "Mineral",
          "original_thoughts": null,
          "thoughts": null,
          "next_article": "Chemical",
          "reasoning": "",
          "language": "English",
          "translated": false
        }
      ],
      "count": 50
    },
    "tank-02-eve": {
      "latest": [
        {
          "timestamp": "2026-02-20T15:49:56.494677",
          "tank": "tank-02-eve",
          "article": "Coral Sea Islands",
          "original_thoughts": null,
          "thoughts": null,
          "next_article": "Tasmania",
          "reasoning": "",
          "language": "English",
          "translated": false
        },
        {
          "timestamp": "2026-02-20T15:49:59.527424",
          "tank": "tank-02-eve",
          "article": "Tasmania",
          "original_thoughts": null,
          "thoughts": null,
          "next_article": "Jeremy Rockliff",
          "reasoning": "",
          "language": "English",
          "translated": false
        },
        {
          "timestamp": "2026-02-20T15:50:02.601784",
          "tank": "tank-02-eve",
          "article": "Jeremy Rockliff",
          "original_thoughts": null,
          "thoughts": null,
          "next_article": "Division of Braddon (state)",
          "reasoning": "",
          "language": "English",
          "translated": false
        },
        {
          "timestamp": "2026-02-20T15:50:05.744077",
          "tank": "tank-02-eve",
          "article": "Division of Braddon (state)",
          "original_thoughts": null,
          "thoughts": null,
          "next_article": "States and territories of Australia",
          "reasoning": "",
          "language": "English",
          "translated": false
        },
        {
          "timestamp": "2026-02-20T15:50:08.782299",
          "tank": "tank-02-eve",
          "article": "States and territories of Australia",
          "original_thoughts": null,
          "thoughts": null,
          "next_article": "Queensland",
          "reasoning": "",
          "language": "English",
          "translated": false
        }
      ],
      "count": 50
    },
    "tank-03-cain": {
      "latest": [
        {
          "timestamp": "2026-02-20T15:49:55.528890",
          "tank": "tank-03-cain",
          "article": "Haredi Judaism",
          "original_thoughts": null,
          "thoughts": null,
          "next_article": "Hasidic Judaism",
          "reasoning": "",
          "language": "English",
          "translated": false
        },
        {
          "timestamp": "2026-02-20T15:49:58.553238",
          "tank": "tank-03-cain",
          "article": "Hasidic Judaism",
          "original_thoughts": null,
          "thoughts": null,
          "next_article": "Judaism",
          "reasoning": "",
          "language": "English",
          "translated": false
        },
        {
          "timestamp": "2026-02-20T15:50:01.615619",
          "tank": "tank-03-cain",
          "article": "Judaism",
          "original_thoughts": null,
          "thoughts": null,
          "next_article": "Orthodox Judaism",
          "reasoning": "",
          "language": "English",
          "translated": false
        },
        {
          "timestamp": "2026-02-20T15:50:04.680107",
          "tank": "tank-03-cain",
          "article": "Orthodox Judaism",
          "original_thoughts": null,
          "thoughts": null,
          "next_article": "Conservative Judaism",
          "reasoning": "",
          "language": "English",
          "translated": false
        },
        {
          "timestamp": "2026-02-20T15:50:07.737604",
          "tank": "tank-03-cain",
          "article": "Conservative Judaism",
          "original_thoughts": null,
          "thoughts": null,
          "next_article": "Hasidic Judaism",
          "reasoning": "",
          "language": "English",
          "translated": false
        }
      ],
      "count": 50
    },
    "tank-04-abel": {
      "latest": [
        {
          "timestamp": "2026-02-20T13:43:35.884764",
          "tank": "tank-04-abel",
          "article": "Hemp",
          "original_thoughts": null,
          "thoughts": null,
          "next_article": "Agriculture",
          "reasoning": "",
          "language": "English",
          "translated": false
        },
        {
          "timestamp": "2026-02-20T13:45:35.914777",
          "tank": "tank-04-abel",
          "article": "Agriculture",
          "original_thoughts": null,
          "thoughts": null,
          "next_article": "Animal husbandry",
          "reasoning": "",
          "language": "English",
          "translated": false
        },
        {
          "timestamp": "2026-02-20T13:47:40.937989",
          "tank": "tank-04-abel",
          "article": "Animal husbandry",
          "original_thoughts": null,
          "thoughts": null,
          "next_article": "United States",
          "reasoning": "",
          "language": "English",
          "translated": false
        },
        {
          "timestamp": "2026-02-20T13:49:40.965930",
          "tank": "tank-04-abel",
          "article": "United States",
          "original_thoughts": null,
          "thoughts": null,
          "next_article": "America (disambiguation)",
          "reasoning": "",
          "language": "English",
          "translated": false
        },
        {
          "timestamp": "2026-02-20T15:54:57.950118",
          "tank": "tank-04-abel",
          "article": "Mathematics",
          "original_thoughts": null,
          "thoughts": null,
          "next_article": "Counting",
          "reasoning": "",
          "language": "English",
          "translated": false
        }
      ],
      "count": 50
    },
    "tank-13-victor": {
      "latest": [
        {
          "timestamp": "2026-02-20T15:49:59.491409",
          "tank": "tank-13-victor",
          "article": "Electron",
          "original_thoughts": null,
          "thoughts": null,
          "next_article": "Atom",
          "reasoning": "",
          "language": "English",
          "translated": false
        },
        {
          "timestamp": "2026-02-20T15:50:02.607385",
          "tank": "tank-13-victor",
          "article": "Atom",
          "original_thoughts": null,
          "thoughts": null,
          "next_article": "Atom (feed)",
          "reasoning": "",
          "language": "English",
          "translated": false
        },
        {
          "timestamp": "2026-02-20T15:50:05.657328",
          "tank": "tank-13-victor",
          "article": "Atom (feed)",
          "original_thoughts": null,
          "thoughts": null,
          "next_article": "HTTP",
          "reasoning": "",
          "language": "English",
          "translated": false
        },
        {
          "timestamp": "2026-02-20T15:50:08.753055",
          "tank": "tank-13-victor",
          "article": "HTTP",
          "original_thoughts": null,
          "thoughts": null,
          "next_article": "Payment",
          "reasoning": "",
          "language": "English",
          "translated": false
        },
        {
          "timestamp": "2026-02-20T15:54:12.043962",
          "tank": "tank-13-victor",
          "article": "Payment",
          "original_thoughts": null,
          "thoughts": null,
          "next_article": "Law",
          "reasoning": "",
          "language": "English",
          "translated": false
        }
      ],
      "count": 50
    },
    "tank-14-iris": {
      "latest": [
        {
          "timestamp": "2026-02-20T15:49:59.288294",
          "tank": "tank-14-iris",
          "article": "Stimulus",
          "original_thoughts": null,
          "thoughts": null,
          "next_article": "Credit",
          "reasoning": "",
          "language": "English",
          "translated": false
        },
        {
          "timestamp": "2026-02-20T15:50:02.302381",
          "tank": "tank-14-iris",
          "article": "Credit",
          "original_thoughts": null,
          "thoughts": null,
          "next_article": "Credit card",
          "reasoning": "",
          "language": "English",
          "translated": false
        },
        {
          "timestamp": "2026-02-20T15:50:05.376533",
          "tank": "tank-14-iris",
          "article": "Credit card",
          "original_thoughts": null,
          "thoughts": null,
          "next_article": "Payment",
          "reasoning": "",
          "language": "English",
          "translated": false
        },
        {
          "timestamp": "2026-02-20T15:50:08.401917",
          "tank": "tank-14-iris",
          "article": "Payment",
          "original_thoughts": null,
          "thoughts": null,
          "next_article": "Debit card",
          "reasoning": "",
          "language": "English",
          "translated": false
        },
        {
          "timestamp": "2026-02-20T15:54:11.704650",
          "tank": "tank-14-iris",
          "article": "Debit card",
          "original_thoughts": null,
          "thoughts": null,
          "next_article": "Plastic",
          "reasoning": "",
          "language": "English",
          "translated": false
        }
      ],
      "count": 50
    },
    "tank-15-observer": {
      "latest": [
        {
          "timestamp": "2026-02-20T15:49:57.736082",
          "tank": "tank-15-observer",
          "article": "Slide rule",
          "original_thoughts": null,
          "thoughts": null,
          "next_article": "Analog computer",
          "reasoning": "",
          "language": "English",
          "translated": false
        },
        {
          "timestamp": "2026-02-20T15:50:00.770988",
          "tank": "tank-15-observer",
          "article": "Analog computer",
          "original_thoughts": null,
          "thoughts": null,
          "next_article": "Device",
          "reasoning": "",
          "language": "English",
          "translated": false
        },
        {
          "timestamp": "2026-02-20T15:50:03.823444",
          "tank": "tank-15-observer",
          "article": "Device",
          "original_thoughts": null,
          "thoughts": null,
          "next_article": "Machine",
          "reasoning": "",
          "language": "English",
          "translated": false
        },
        {
          "timestamp": "2026-02-20T15:50:06.839011",
          "tank": "tank-15-observer",
          "article": "Machine",
          "original_thoughts": null,
          "thoughts": null,
          "next_article": "Tool",
          "reasoning": "",
          "language": "English",
          "translated": false
        },
        {
          "timestamp": "2026-02-20T15:54:10.152347",
          "tank": "tank-15-observer",
          "article": "Tool",
          "original_thoughts": null,
          "thoughts": null,
          "next_article": "Stone Age",
          "reasoning": "",
          "language": "English",
          "translated": false
        }
      ],
      "count": 50
    },
    "tank-16-seeker": {
      "latest": [
        {
          "timestamp": "2026-02-20T15:49:59.049546",
          "tank": "tank-16-seeker",
          "article": "Bowing",
          "original_thoughts": null,
          "thoughts": null,
          "next_article": "Greeting",
          "reasoning": "",
          "language": "English",
          "translated": false
        },
        {
          "timestamp": "2026-02-20T15:50:02.098592",
          "tank": "tank-16-seeker",
          "article": "Greeting",
          "original_thoughts": null,
          "thoughts": null,
          "next_article": "Culture",
          "reasoning": "",
          "language": "English",
          "translated": false
        },
        {
          "timestamp": "2026-02-20T15:50:05.140281",
          "tank": "tank-16-seeker",
          "article": "Culture",
          "original_thoughts": null,
          "thoughts": null,
          "next_article": "Writing",
          "reasoning": "",
          "language": "English",
          "translated": false
        },
        {
          "timestamp": "2026-02-20T15:50:08.166210",
          "tank": "tank-16-seeker",
          "article": "Writing",
          "original_thoughts": null,
          "thoughts": null,
          "next_article": "Text",
          "reasoning": "",
          "language": "English",
          "translated": false
        },
        {
          "timestamp": "2026-02-20T15:54:11.438915",
          "tank": "tank-16-seeker",
          "article": "Text",
          "original_thoughts": null,
          "thoughts": null,
          "next_article": "Book",
          "reasoning": "",
          "language": "English",
          "translated": false
        }
      ],
      "count": 50
    },
    "tank-17-seth": {
      "latest": [
        {
          "timestamp": "2026-02-20T15:49:59.477070",
          "tank": "tank-17-seth",
          "article": "Biology",
          "original_thoughts": null,
          "thoughts": null,
          "next_article": "Microorganisms",
          "reasoning": "",
          "language": "English",
          "translated": false
        },
        {
          "timestamp": "2026-02-20T15:50:02.502744",
          "tank": "tank-17-seth",
          "article": "Microorganisms",
          "original_thoughts": null,
          "thoughts": null,
          "next_article": "Unicellular organism",
          "reasoning": "",
          "language": "English",
          "translated": false
        },
        {
          "timestamp": "2026-02-20T15:50:05.541825",
          "tank": "tank-17-seth",
          "article": "Unicellular organism",
          "original_thoughts": null,
          "thoughts": null,
          "next_article": "Microorganism",
          "reasoning": "",
          "language": "English",
          "translated": false
        },
        {
          "timestamp": "2026-02-20T15:50:08.557367",
          "tank": "tank-17-seth",
          "article": "Microorganism",
          "original_thoughts": null,
          "thoughts": null,
          "next_article": "Organism",
          "reasoning": "",
          "language": "English",
          "translated": false
        },
        {
          "timestamp": "2026-02-20T15:53:11.809287",
          "tank": "tank-17-seth",
          "article": "Organism",
          "original_thoughts": null,
          "thoughts": null,
          "next_article": "Energy",
          "reasoning": "",
          "language": "English",
          "translated": false
        }
      ],
      "count": 50
    }
  }
}