{
  "name": "Seeker",
  "emoji": "\ud83d\udd0d",
  "type": "Special",
  "status": "active",
  "traces_12h": 20,
  "latest_baseline": null,
  "recent_thoughts": [
    {
      "time": "18:34",
      "date": "2026-02-21",
      "article": "Set theory",
      "thought": "Exploring Set theory...",
      "next": "Bertrand Russell"
    },
    {
      "time": "18:30",
      "date": "2026-02-21",
      "article": "Object",
      "thought": "Exploring Object...",
      "next": "Set theory"
    },
    {
      "time": "18:26",
      "date": "2026-02-21",
      "article": "Symbol",
      "thought": "Exploring Symbol...",
      "next": "Object"
    },
    {
      "time": "18:22",
      "date": "2026-02-21",
      "article": "National flag",
      "thought": "Exploring National flag...",
      "next": "Symbol"
    },
    {
      "time": "18:18",
      "date": "2026-02-21",
      "article": "National anthem",
      "thought": "Exploring National anthem...",
      "next": "National flag"
    },
    {
      "time": "18:14",
      "date": "2026-02-21",
      "article": "Royal anthem",
      "thought": "Exploring Royal anthem...",
      "next": "National anthem"
    },
    {
      "time": "18:10",
      "date": "2026-02-21",
      "article": "Canada",
      "thought": "Exploring Canada...",
      "next": "Royal anthem"
    },
    {
      "time": "18:06",
      "date": "2026-02-21",
      "article": "English language",
      "thought": "Exploring English language...",
      "next": "Canada"
    },
    {
      "time": "18:02",
      "date": "2026-02-21",
      "article": "Phrase",
      "thought": "Exploring Phrase...",
      "next": "English language"
    },
    {
      "time": "17:58",
      "date": "2026-02-21",
      "article": "Code",
      "thought": "Exploring Code...",
      "next": "Phrase"
    }
  ],
  "top_topics": [
    {
      "topic": "Emotion",
      "visits": 11
    },
    {
      "topic": "Atom",
      "visits": 9
    },
    {
      "topic": "Language",
      "visits": 7
    },
    {
      "topic": "Number",
      "visits": 6
    },
    {
      "topic": "Earth",
      "visits": 6
    },
    {
      "topic": "Acceptance",
      "visits": 6
    },
    {
      "topic": "United States",
      "visits": 5
    },
    {
      "topic": "Continent",
      "visits": 5
    }
  ]
}